energium_protocol_sdk/__init__.py
energium_protocol_sdk/fields/__init__.py
energium_protocol_sdk/fields/base.py
energium_protocol_sdk/fields/patient.py
energium_protocol_sdk/fields/reception.py
energium_protocol_sdk/models.py
energium_protocol_sdk-0.0.5.dist-info/WHEEL
energium_protocol_sdk-0.0.5.dist-info/METADATA
energium_protocol_sdk-0.0.5.dist-info/RECORD
