Metadata-Version: 2.1
Name: energium-protocol-sdk
Version: 0.0.5
Summary: 
Author: dyus
Author-email: dyuuus@gmail.com
Requires-Python: >=3.9,<4.0
Classifier: Programming Language :: Python :: 3
Classifier: Programming Language :: Python :: 3.10
Classifier: Programming Language :: Python :: 3.9
Requires-Dist: pydantic (>=1.10.2,<2.0.0)
